folderify/__init__.py
folderify/__main__.py
folderify/GenericFolderIcon.BigSur.dark.iconset/icon_128x128.png
folderify/GenericFolderIcon.BigSur.dark.iconset/icon_128x128@2x.png
folderify/GenericFolderIcon.BigSur.dark.iconset/icon_16x16.png
folderify/GenericFolderIcon.BigSur.dark.iconset/icon_16x16@2x.png
folderify/GenericFolderIcon.BigSur.dark.iconset/icon_256x256.png
folderify/GenericFolderIcon.BigSur.dark.iconset/icon_256x256@2x.png
folderify/GenericFolderIcon.BigSur.dark.iconset/icon_32x32.png
folderify/GenericFolderIcon.BigSur.dark.iconset/icon_32x32@2x.png
folderify/GenericFolderIcon.BigSur.dark.iconset/icon_512x512.png
folderify/GenericFolderIcon.BigSur.dark.iconset/icon_512x512@2x.png
folderify/GenericFolderIcon.BigSur.iconset/icon_128x128.png
folderify/GenericFolderIcon.BigSur.iconset/icon_128x128@2x.png
folderify/GenericFolderIcon.BigSur.iconset/icon_16x16.png
folderify/GenericFolderIcon.BigSur.iconset/icon_16x16@2x.png
folderify/GenericFolderIcon.BigSur.iconset/icon_256x256.png
folderify/GenericFolderIcon.BigSur.iconset/icon_256x256@2x.png
folderify/GenericFolderIcon.BigSur.iconset/icon_32x32.png
folderify/GenericFolderIcon.BigSur.iconset/icon_32x32@2x.png
folderify/GenericFolderIcon.BigSur.iconset/icon_512x512.png
folderify/GenericFolderIcon.BigSur.iconset/icon_512x512@2x.png
folderify/GenericFolderIcon.Leopard.iconset/icon_128x128.png
folderify/GenericFolderIcon.Leopard.iconset/icon_128x128@2x.png
folderify/GenericFolderIcon.Leopard.iconset/icon_16x16.png
folderify/GenericFolderIcon.Leopard.iconset/icon_16x16@2x.png
folderify/GenericFolderIcon.Leopard.iconset/icon_256x256.png
folderify/GenericFolderIcon.Leopard.iconset/icon_256x256@2x.png
folderify/GenericFolderIcon.Leopard.iconset/icon_32x32.png
folderify/GenericFolderIcon.Leopard.iconset/icon_32x32@2x.png
folderify/GenericFolderIcon.Leopard.iconset/icon_512x512.png
folderify/GenericFolderIcon.Leopard.iconset/icon_512x512@2x.png
folderify/GenericFolderIcon.Yosemite.iconset/icon_128x128.png
folderify-2.4.2.dist-info/LICENSE.md
folderify-2.4.2.dist-info/METADATA
folderify-2.4.2.dist-info/WHEEL
folderify-2.4.2.dist-info/entry_points.txt
folderify-2.4.2.dist-info/top_level.txt
folderify-2.4.2.dist-info/RECORD
