Metadata-Version: 2.1
Name: folderify
Version: 2.4.2
Summary: Generate pixel-perfect macOS folder icons in the native style.
Home-page: https://github.com/lgarron/folderify
Author: Lucas Garron
Author-email: code@garron.net
License: MIT
Keywords: icon macOS OSX Mac Darwin graphics folder imagemagick
Platform: UNKNOWN
Classifier: Development Status :: 5 - Production/Stable
Classifier: Intended Audience :: Developers
Classifier: Topic :: Multimedia :: Graphics
Classifier: Topic :: Software Development :: Build Tools
Classifier: Topic :: Software Development :: Libraries
Classifier: Topic :: Utilities
Classifier: License :: OSI Approved :: MIT License
Classifier: Programming Language :: Python :: 2
Classifier: Programming Language :: Python :: 2.6
Classifier: Programming Language :: Python :: 2.7
License-File: LICENSE.md
